footballtestdata/__init__.py
footballtestdata/data.py
footballtestdata/generator.py
footballtestdata-1.3.dist-info/LICENSE
footballtestdata-1.3.dist-info/METADATA
footballtestdata-1.3.dist-info/WHEEL
footballtestdata-1.3.dist-info/top_level.txt
footballtestdata-1.3.dist-info/RECORD
