Metadata-Version: 2.1
Name: footballtestdata
Version: 1.3
Summary: A package to generate fake footballer data
Home-page: https://mazarzycki.com/
Author: Marek Zarzycki
Author-email: contact@mazarzycki.com
Keywords: python,football,soccer,data
Classifier: Development Status :: 5 - Production/Stable
Classifier: Intended Audience :: Developers
Classifier: License :: OSI Approved :: MIT License
Classifier: Operating System :: OS Independent
Classifier: Programming Language :: Python :: 3
Classifier: Topic :: Software Development :: Libraries :: Python Modules
License-File: LICENSE
